{
  "Dataset": {
    "AtomTypeStyle": "chemicalsymbol",
    "Data": [
      {
        "AtomTypes": [
          "Au",
          "Au",
          "Au",
          "Au"
        ],
        "Energy": -41366.26768562542,
        "Forces": [
          [
            -0.0,
            0.0,
            -0.0
          ],
          [
            0.0,
            -0.0,
            -0.0
          ],
          [
            0.0,
            -0.0,
            0.0
          ],
          [
            0.0,
            0.0,
            -0.0
          ]
        ],
        "Lattice": [
          [
            -1.957955670908103,
            0.0,
            1.957955670908103
          ],
          [
            0.0,
            1.957955670908103,
            1.957955670908103
          ],
          [
            -1.957955670908103,
            1.957955670908103,
            0.0
          ]
        ],
        "NumAtoms": 4,
        "Positions": [
          [
            0.0,
            0.0,
            0.0
          ],
          [
            0.0,
            0.9789778354540515,
            0.9789778354540515
          ],
          [
            0.9789778354540515,
            0.0,
            0.9789778354540515
          ],
          [
            0.9789778354540515,
            0.9789778354540515,
            0.0
          ]
        ],
        "Stress": [
          [
            0.0,
            0.0,
            0.0
          ],
          [
            0.0,
            0.0,
            0.0
          ],
          [
            0.0,
            0.0,
            0.0
          ]
        ]
      }
    ],
    "EnergyStyle": "electronvolt",
    "ForcesStyle": "electronvoltperangstrom",
    "Label": "ASE generated",
    "LatticeStyle": "angstrom",
    "PositionsStyle": "angstrom",
    "StressStyle": "kB"
  }
}