{
  "Dataset": {
    "AtomTypeStyle": "chemicalsymbol",
    "Data": [
      {
        "AtomTypes": [
          "Au",
          "Au",
          "Au",
          "Au",
          "Au",
          "Au",
          "Au",
          "Au",
          "Au",
          "Au"
        ],
        "Energy": -105461.82423914623,
        "Forces": [
          [
            -0.01320211118477341,
            -5.142210479385141e-07,
            -1.0284420958770282e-06
          ],
          [
            0.014548856109324378,
            -2.0568841917540564e-06,
            2.5711052396925704e-07
          ],
          [
            0.024757943684571668,
            4.113768383508113e-06,
            2.3139947157233134e-06
          ],
          [
            -0.021391081373194246,
            1.2855526198462852e-06,
            -1.2855526198462852e-06
          ],
          [
            0.009993886066685023,
            -5.142210479385141e-07,
            1.0284420958770282e-06
          ],
          [
            -0.010794528238325288,
            -1.5426631438155423e-06,
            -7.713315719077711e-07
          ],
          [
            0.020536960212568376,
            -7.713315719077711e-07,
            -2.828215763661828e-06
          ],
          [
            -0.024434498645418343,
            1.0284420958770282e-06,
            1.2855526198462852e-06
          ],
          [
            -0.013594461844350496,
            0.0,
            -5.142210479385141e-07
          ],
          [
            0.013579549433960279,
            -1.0284420958770282e-06,
            1.0284420958770282e-06
          ]
        ],
        "Lattice": [
          [
            23.55195665953456,
            0.0,
            0.0
          ],
          [
            0.0,
            2.94399458244182,
            0.0
          ],
          [
            0.0,
            0.0,
            4.163444242402541
          ]
        ],
        "NumAtoms": 10,
        "Positions": [
          [
            0.09282622646696796,
            0.0,
            0.0
          ],
          [
            1.3689866405129865,
            1.47199729122091,
            2.0817221212012704
          ],
          [
            2.9638742850462605,
            0.0,
            0.0
          ],
          [
            4.394583762120478,
            1.47199729122091,
            2.0817221212012704
          ],
          [
            5.894453352668199,
            0.0,
            0.0
          ],
          [
            7.353885147447419,
            1.47199729122091,
            2.0817221212012704
          ],
          [
            8.853703229865927,
            0.0,
            0.0
          ],
          [
            10.284096286402422,
            1.47199729122091,
            2.0817221212012704
          ],
          [
            11.878771522904172,
            0.0,
            0.0
          ],
          [
            13.154697651506122,
            1.47199729122091,
            2.0817221212012704
          ]
        ],
        "Stress": [
          [
            0.0,
            0.0,
            0.0
          ],
          [
            0.0,
            0.0,
            0.0
          ],
          [
            0.0,
            0.0,
            0.0
          ]
        ]
      }
    ],
    "EnergyStyle": "electronvolt",
    "ForcesStyle": "electronvoltperangstrom",
    "Label": "ASE generated",
    "LatticeStyle": "angstrom",
    "PositionsStyle": "angstrom",
    "StressStyle": "kB"
  }
}