{
  "Dataset": {
    "AtomTypeStyle": "chemicalsymbol",
    "Data": [
      {
        "AtomTypes": [
          "Au",
          "Au"
        ],
        "Energy": -20989.65535651154,
        "Forces": [
          [
            0.0,
            0.0,
            0.0
          ],
          [
            0.0,
            0.0,
            0.0
          ]
        ],
        "Lattice": [
          [
            1.6933670667313323,
            1.6933670667313323,
            1.6933670667313323
          ],
          [
            -1.6933670667313323,
            1.6933670667313323,
            1.6933670667313323
          ],
          [
            -1.6933670667313323,
            -1.6933670667313323,
            1.6933670667313323
          ]
        ],
        "NumAtoms": 2,
        "Positions": [
          [
            0.0,
            0.0,
            0.0
          ],
          [
            -0.8466835333656662,
            0.8466835333656662,
            2.5400506000969987
          ]
        ],
        "Stress": [
          [
            0.0,
            0.0,
            0.0
          ],
          [
            0.0,
            0.0,
            0.0
          ],
          [
            0.0,
            0.0,
            0.0
          ]
        ]
      }
    ],
    "EnergyStyle": "electronvolt",
    "ForcesStyle": "electronvoltperangstrom",
    "Label": "ASE generated",
    "LatticeStyle": "angstrom",
    "PositionsStyle": "angstrom",
    "StressStyle": "kB"
  }
}