{
  "Dataset": {
    "AtomTypeStyle": "chemicalsymbol",
    "Data": [
      {
        "AtomTypes": [
          "Au",
          "Au"
        ],
        "Energy": -21086.55653835212,
        "Forces": [
          [
            0.007146129903201531,
            0.00535741198794741,
            0.009047976449002125
          ],
          [
            -0.007146129903201531,
            -0.00535741198794741,
            -0.009047976449002125
          ]
        ],
        "Lattice": [
          [
            6.266490571639427,
            0.004568271626725142,
            0.0007457123780250919
          ],
          [
            0.00038225592487000504,
            6.255843804158211,
            0.004862796683592195
          ],
          [
            0.004430408834149074,
            0.0038852241544164445,
            6.273339845834228
          ]
        ],
        "NumAtoms": 2,
        "Positions": [
          [
            0.0,
            0.0,
            0.0
          ],
          [
            3.124333709577785,
            3.124333709577785,
            3.124333709577785
          ]
        ],
        "Stress": [
          [
            0.0,
            0.0,
            0.0
          ],
          [
            0.0,
            0.0,
            0.0
          ],
          [
            0.0,
            0.0,
            0.0
          ]
        ]
      }
    ],
    "EnergyStyle": "electronvolt",
    "ForcesStyle": "electronvoltperangstrom",
    "Label": "ASE generated",
    "LatticeStyle": "angstrom",
    "PositionsStyle": "angstrom",
    "StressStyle": "kB"
  }
}